{
  "$schema": "https://static.modelcontextprotocol.io/schemas/2025-12-11/server.schema.json",
  "name": "io.github.pipeworx-io/sec",
  "title": "sec",
  "description": "SEC MCP — SEC EDGAR public APIs (free, no auth)",
  "version": "0.1.0",
  "websiteUrl": "https://pipeworx.io/packs/sec",
  "repository": {
    "url": "https://github.com/pipeworx-io/mcp-sec",
    "source": "github"
  },
  "packages": [
    {
      "registryType": "npm",
      "identifier": "@pipeworx/mcp-sec",
      "version": "0.1.0"
    }
  ],
  "remotes": [
    {
      "type": "streamable-http",
      "url": "https://gateway.pipeworx.io/sec/mcp"
    }
  ]
}
